streamlit_overlay/__init__.py
streamlit_overlay/utils.py
streamlit_overlay/frontend/build/index.html
streamlit_overlay/frontend/build/assets/index-BeVRhPBe.css
streamlit_overlay/frontend/build/assets/index-mw35SBtc.js
streamlit_overlay-0.0.1.dist-info/LICENSE
streamlit_overlay-0.0.1.dist-info/METADATA
streamlit_overlay-0.0.1.dist-info/WHEEL
streamlit_overlay-0.0.1.dist-info/top_level.txt
streamlit_overlay-0.0.1.dist-info/RECORD
