Metadata-Version: 2.1
Name: streamlit-overlay
Version: 0.0.1
Summary: Streamlit component that allows you add overlays to images
Home-page: 
Author: Jens Rahnfeld
Author-email: 
Project-URL: Homepage, https://github.com/JensRahnfeld/streamlit-overlay
Project-URL: Issues, https://github.com/JensRahnfeld/streamlit-overlay/issues
Classifier: Programming Language :: Python :: 3
Classifier: License :: OSI Approved :: MIT License
Requires-Python: >=3.8
License-File: LICENSE
Requires-Dist: opencv-python >=4.6.0.66
Requires-Dist: streamlit >=1.22.0
